pysegmenters_spacyrules/__init__.py
pysegmenters_spacyrules/rule_sentencizer.py
pysegmenters_spacyrules/spacyrules.py
pysegmenters_spacyrules-0.4.13.dist-info/entry_points.txt
pysegmenters_spacyrules-0.4.13.dist-info/LICENSE
pysegmenters_spacyrules-0.4.13.dist-info/WHEEL
pysegmenters_spacyrules-0.4.13.dist-info/METADATA
pysegmenters_spacyrules-0.4.13.dist-info/RECORD
