Metadata-Version: 2.1
Name: pysegmenters-spacyrules
Version: 0.4.13
Summary: Segmenter based on Spacy
Home-page: https://github.com/oterrier/pysegmenters_spacyrules/
Keywords: 
Author: Olivier Terrier
Author-email: olivier.terrier@kairntech.com
Requires-Python: >=3.8
Classifier: Intended Audience :: Information Technology
Classifier: Intended Audience :: Developers
Classifier: Intended Audience :: System Administrators
Classifier: Operating System :: OS Independent
Classifier: Topic :: Software Development :: Libraries :: Application Frameworks
Classifier: Topic :: Software Development :: Libraries :: Python Modules
Classifier: Topic :: Software Development :: Libraries
Classifier: Topic :: Software Development
Classifier: License :: OSI Approved :: MIT License
Classifier: Development Status :: 4 - Beta
Classifier: Programming Language :: Python :: 3.8
Requires-Dist: pymultirole-plugins>=0.4.0,<0.5.0
Requires-Dist: spacy==3.0.6
Requires-Dist: spacy[lookups]
Requires-Dist: flit ; extra == "dev"
Requires-Dist: pre-commit ; extra == "dev"
Requires-Dist: bump2version ; extra == "dev"
Requires-Dist: sphinx ; extra == "docs"
Requires-Dist: sphinx-rtd-theme ; extra == "docs"
Requires-Dist: m2r2 ; extra == "docs"
Requires-Dist: sphinxcontrib.apidoc ; extra == "docs"
Requires-Dist: jupyter_sphinx ; extra == "docs"
Requires-Dist: pytest ; extra == "test"
Requires-Dist: pytest-cov ; extra == "test"
Requires-Dist: pytest-flake8 ; extra == "test"
Requires-Dist: pytest-black ; extra == "test"
Requires-Dist: hypothesis ; extra == "test"
Requires-Dist: tox ; extra == "test"
Provides-Extra: dev
Provides-Extra: docs
Provides-Extra: test
